vdst/__init__.py
vdst/template.py
vdst-0.3.dist-info/METADATA
vdst-0.3.dist-info/WHEEL
vdst-0.3.dist-info/entry_points.txt
vdst-0.3.dist-info/top_level.txt
vdst-0.3.dist-info/RECORD
